nameko_apscheduler/__init__.py
nameko_apscheduler/schedulers.py
nameko_apscheduler/schema.py
nameko_apscheduler/utils.py
nameko_apscheduler-0.2.0.dist-info/LICENSE
nameko_apscheduler-0.2.0.dist-info/METADATA
nameko_apscheduler-0.2.0.dist-info/WHEEL
nameko_apscheduler-0.2.0.dist-info/top_level.txt
nameko_apscheduler-0.2.0.dist-info/zip-safe
nameko_apscheduler-0.2.0.dist-info/RECORD
