Metadata-Version: 2.1
Name: nameko-apscheduler
Version: 0.2.0
Summary: nameko apscheduler dependency.
Home-page: https://github.com/ma-pony/nameko-apscheduler
Author: Pony Ma
Author-email: mtf201013@gmail.com
License: Apache License, Version 2.0
Platform: UNKNOWN
Classifier: Programming Language :: Python :: 3
Requires-Dist: marshmallow (>=2.20.0)
Requires-Dist: nameko (>=3.0.0-rc6)
Requires-Dist: kombu (>=4.6.8)
Requires-Dist: APScheduler (>=3.6.3)
